generss/__init__.py
generss/util.py
generss-0.3.3.dist-info/LICENSE
generss-0.3.3.dist-info/METADATA
generss-0.3.3.dist-info/WHEEL
generss-0.3.3.dist-info/entry_points.txt
generss-0.3.3.dist-info/top_level.txt
generss-0.3.3.dist-info/RECORD
