Metadata-Version: 2.1
Name: generss
Version: 0.3.3
Summary: Generate RSS feeds from media files in a directory
Author: Amine Sehili
Author-email: Amine Sehili <amine.sehili@gmail.com>
License: MIT License
Project-URL: homepage, https://pypi.org/project/generss/
Project-URL: repository, https://github.com/amsehili/genRSS
Keywords: RSS,podcast
Classifier: Development Status :: 3 - Alpha
Classifier: Environment :: Console
Classifier: Intended Audience :: Developers
Classifier: Intended Audience :: End Users/Desktop
Classifier: Intended Audience :: Information Technology
Classifier: License :: OSI Approved :: MIT License
Classifier: Programming Language :: Python
Classifier: Programming Language :: Python :: 3
Classifier: Programming Language :: Python :: 3.6
Classifier: Programming Language :: Python :: 3.7
Classifier: Programming Language :: Python :: 3.8
Classifier: Programming Language :: Python :: 3.9
Classifier: Programming Language :: Python :: 3.10
Classifier: Programming Language :: Python :: 3.11
Classifier: Programming Language :: Python :: 3.12
Classifier: Programming Language :: Python :: 3.13
Classifier: Topic :: Communications :: File Sharing
Classifier: Topic :: Utilities
Requires-Python: >=3.4
License-File: LICENSE
Requires-Dist: mutagen (>=1.47)
Requires-Dist: eyed3 (>=0.9.7)
